Workbook

Sheet 客户版·决策对比表
A1: 店算 · 小店决策对比表（示例：小面 · 30㎡）
A2: 一眼看懂版：不同房租下，每天要做到多少营业额。参数由店算按业态自动预置，客户不需要填任何专业指标。
A4: 一、本次测算使用的行业预置参数（改这里，全表自动重算）
A5: 业态 | B5: 菜品毛利率 | C5: 水电燃气 | D5: 管理费 | E5: 杂支损耗 | F5: 人工单价(元/人·月) | G5: 月营业天数 | H5: 边际贡献率 | I5: 客单价(元)
A6: 小面（快餐） | B6: 0.6 | C6: 0.03 | D6: 0.08 | E6: 0.02 | F6: 4500 | G6: 30 | H6: =1-(1-B6)-C6-D6-E6 -> 0.47 | I6: 12 | J6: 边际贡献率 = 1 − 食材成本率 − 水电燃气 − 管理费 − 杂支损耗；食材成本率 = 1 − 菜品毛利率（内部量，不对外展示）。最右一列「日碗数」为单品业态（小面/米粉等）专属，其他业态请忽略该列。
A8: 二、已有铺面测算：每天要做到多少营业额（元 / 天）
A9: 月租金(元) | B9: 员工人数(人) | C9: 月固定成本(元) | D9: 保本·日营业额(元) | E9: 月赚1万·日营业额(元) | F9: 月赚1.5万·日营业额(元) | G9: 保本·月营业额(元) | H9: 保本·日碗数(碗)〔可选〕
A10: 3000 | B10: 2 | C10: =A10+B10*$F$6 -> 12000 | D10: =ROUND((C10+0)/$H$6/$G$6,0) -> 851 | E10: =ROUND((C10+10000)/$H$6/$G$6,0) -> 1560 | F10: =ROUND((C10+15000)/$H$6/$G$6,0) -> 1915 | G10: =ROUND(C10/$H$6,0) -> 25532 | H10: =ROUNDUP((C10/$H$6)/$I$6/$G$6,0) -> 71
A11: 4000 | B11: 2 | C11: =A11+B11*$F$6 -> 13000 | D11: =ROUND((C11+0)/$H$6/$G$6,0) -> 922 | E11: =ROUND((C11+10000)/$H$6/$G$6,0) -> 1631 | F11: =ROUND((C11+15000)/$H$6/$G$6,0) -> 1986 | G11: =ROUND(C11/$H$6,0) -> 27660 | H11: =ROUNDUP((C11/$H$6)/$I$6/$G$6,0) -> 77
A12: 5000 | B12: 2 | C12: =A12+B12*$F$6 -> 14000 | D12: =ROUND((C12+0)/$H$6/$G$6,0) -> 993 | E12: =ROUND((C12+10000)/$H$6/$G$6,0) -> 1702 | F12: =ROUND((C12+15000)/$H$6/$G$6,0) -> 2057 | G12: =ROUND(C12/$H$6,0) -> 29787 | H12: =ROUNDUP((C12/$H$6)/$I$6/$G$6,0) -> 83
A13: 6000 | B13: 2 | C13: =A13+B13*$F$6 -> 15000 | D13: =ROUND((C13+0)/$H$6/$G$6,0) -> 1064 | E13: =ROUND((C13+10000)/$H$6/$G$6,0) -> 1773 | F13: =ROUND((C13+15000)/$H$6/$G$6,0) -> 2128 | G13: =ROUND(C13/$H$6,0) -> 31915 | H13: =ROUNDUP((C13/$H$6)/$I$6/$G$6,0) -> 89
A14: 7000 | B14: 2 | C14: =A14+B14*$F$6 -> 16000 | D14: =ROUND((C14+0)/$H$6/$G$6,0) -> 1135 | E14: =ROUND((C14+10000)/$H$6/$G$6,0) -> 1844 | F14: =ROUND((C14+15000)/$H$6/$G$6,0) -> 2199 | G14: =ROUND(C14/$H$6,0) -> 34043 | H14: =ROUNDUP((C14/$H$6)/$I$6/$G$6,0) -> 95
A15: 8000 | B15: 2 | C15: =A15+B15*$F$6 -> 17000 | D15: =ROUND((C15+0)/$H$6/$G$6,0) -> 1206 | E15: =ROUND((C15+10000)/$H$6/$G$6,0) -> 1915 | F15: =ROUND((C15+15000)/$H$6/$G$6,0) -> 2270 | G15: =ROUND(C15/$H$6,0) -> 36170 | H15: =ROUNDUP((C15/$H$6)/$I$6/$G$6,0) -> 101
A16: 9000 | B16: 2 | C16: =A16+B16*$F$6 -> 18000 | D16: =ROUND((C16+0)/$H$6/$G$6,0) -> 1277 | E16: =ROUND((C16+10000)/$H$6/$G$6,0) -> 1986 | F16: =ROUND((C16+15000)/$H$6/$G$6,0) -> 2340 | G16: =ROUND(C16/$H$6,0) -> 38298 | H16: =ROUNDUP((C16/$H$6)/$I$6/$G$6,0) -> 107
A17: 10000 | B17: 2 | C17: =A17+B17*$F$6 -> 19000 | D17: =ROUND((C17+0)/$H$6/$G$6,0) -> 1348 | E17: =ROUND((C17+10000)/$H$6/$G$6,0) -> 2057 | F17: =ROUND((C17+15000)/$H$6/$G$6,0) -> 2411 | G17: =ROUND(C17/$H$6,0) -> 40426 | H17: =ROUNDUP((C17/$H$6)/$I$6/$G$6,0) -> 113
A18: 3000 | B18: 3 | C18: =A18+B18*$F$6 -> 16500 | D18: =ROUND((C18+0)/$H$6/$G$6,0) -> 1170 | E18: =ROUND((C18+10000)/$H$6/$G$6,0) -> 1879 | F18: =ROUND((C18+15000)/$H$6/$G$6,0) -> 2234 | G18: =ROUND(C18/$H$6,0) -> 35106 | H18: =ROUNDUP((C18/$H$6)/$I$6/$G$6,0) -> 98
A19: 4000 | B19: 3 | C19: =A19+B19*$F$6 -> 17500 | D19: =ROUND((C19+0)/$H$6/$G$6,0) -> 1241 | E19: =ROUND((C19+10000)/$H$6/$G$6,0) -> 1950 | F19: =ROUND((C19+15000)/$H$6/$G$6,0) -> 2305 | G19: =ROUND(C19/$H$6,0) -> 37234 | H19: =ROUNDUP((C19/$H$6)/$I$6/$G$6,0) -> 104
A20: 5000 | B20: 3 | C20: =A20+B20*$F$6 -> 18500 | D20: =ROUND((C20+0)/$H$6/$G$6,0) -> 1312 | E20: =ROUND((C20+10000)/$H$6/$G$6,0) -> 2021 | F20: =ROUND((C20+15000)/$H$6/$G$6,0) -> 2376 | G20: =ROUND(C20/$H$6,0) -> 39362 | H20: =ROUNDUP((C20/$H$6)/$I$6/$G$6,0) -> 110
A21: 6000 | B21: 3 | C21: =A21+B21*$F$6 -> 19500 | D21: =ROUND((C21+0)/$H$6/$G$6,0) -> 1383 | E21: =ROUND((C21+10000)/$H$6/$G$6,0) -> 2092 | F21: =ROUND((C21+15000)/$H$6/$G$6,0) -> 2447 | G21: =ROUND(C21/$H$6,0) -> 41489 | H21: =ROUNDUP((C21/$H$6)/$I$6/$G$6,0) -> 116
... A25: 10000 | B25: 3 | C25: =A25+B25*$F$6 -> 23500 | D25: =ROUND((C25+0)/$H$6/$G$6,0) -> 1667 | E25: =ROUND((C25+10000)/$H$6/$G$6,0) -> 2376 | F25: =ROUND((C25+15000)/$H$6/$G$6,0) -> 2730 | G25: =ROUND(C25/$H$6,0) -> 50000 | H25: =ROUNDUP((C25/$H$6)/$I$6/$G$6,0) -> 139
A27: ⚠️ 测算仅供决策参考：以上结果基于【小面·快餐】行业通用参数估算，实际经营受选址、客流、管理水平影响会有较大偏差。若你的门店成本结构与行业默认差异较大，请修改上表参数后重新测算。

Sheet 业态参数包
A1: 店算 · 业态参数包（行业预置，单源）
A2: 核心纪律：每个业态整套参数独立配置，禁止只改食材率、其余沿用别业态模板。
A4: 参数项 | B4: 单位 | C4: 小面（快餐） | D4: 火锅 | E4: 新式奶茶 | F4: 烧烤 | G4: 取值依据 / 来源
A5: 菜品毛利率 | B5: % | C5: 0.6 | D5: 0.55 | E5: 0.68 | F5: 0.58 | G5: 仓内行业参考带 58~68 / 52~67 / 62~72 / 55~65；取带内偏保守值
A6: 水电燃气 | B6: % | C6: 0.03 | D6: 0.05 | E6: 0.02 | F6: 0.04 | G6: 参考带 2~4 / 4~6 / 1~3 / 3~5。⚠️ 外部口径称火锅 8~12%，与仓内单源冲突，待核
A7: 管理费 | B7: % | C7: 0.08 | D7: 0.08 | E7: 0.08 | F7: 0.08 | G7: 参考带 5~10；四业态暂取中值 8%
A8: 杂支损耗 | B8: % | C8: 0.02 | D8: 0.03 | E8: 0.02 | F8: 0.04 | G8: 小面沿用客户原表 2%；其余为我方自定值，待样本校准
A9: 人工单价 | B9: 元/人·月 | C9: 4500 | D9: 5000 | E9: 4500 | F9: 4800 | G9: 小面沿用客户原表 4500。⚠️ 其余为自定值，随城市层级系数联动，待校准
A10: 月营业天数 | B10: 天 | C10: 30 | D10: 27 | E10: 30 | F10: 26 | G10: 快餐/奶茶多为 30 天；火锅月休 4~6 天；烧烤夜宵市场天数偏少
A11: 客单价 | B11: 元 | C11: 12 | D11: 85 | E11: 15 | F11: 60 | G11: 小面沿用客户原表 12。⚠️ 其余为自定值，待校准
A12: 边际贡献率 | B12: % | C12: =1-(1-C5)-C6-C7-C8 -> 0.47 | D12: =1-(1-D5)-D6-D7-D8 -> 0.39 | E12: =1-(1-E5)-E6-E7-E8 -> 0.56 | F12: =1-(1-F5)-F6-F7-F8 -> 0.42 | G12: 边际贡献率 = 1 − 食材成本率 − 水电燃气 − 管理费 − 杂支损耗（由左侧参数自动算出）
A14: 口径说明：① 本表把水电燃气、管理费、杂支损耗按「随营业额变动的费率」处理，与客户原《小面测算》一致，小白无需估算金额；② 店算主引擎的固定成本科目仍支持按金额录入，两套口径由「入参变换」切换，引擎本身无需改动；③ 标 ⚠️ 的取值为待校准项，落地前需用真实门店样本回归。

Sheet 多业态对照
A1: 多业态对照：同一家店，换个业态，门槛差多少
A2: 统一条件：面积 30㎡ ｜ 月租金 5,000 元 ｜ 员工 2 人 ｜ 目标：月净赚 1 万元
A4: 业态 | B4: 月人工(元) | C4: 月固定成本(元) | D4: 边际贡献率 | E4: 保本·日营业额(元) | F4: 月赚1万·日营业额(元) | G4: 月赚1万·月营业额(元) | H4: 说明
A5: 小面（快餐） | B5: =2*业态参数包!C9 -> 9000 | C5: =5000+B5 -> 14000 | D5: =业态参数包!C12 -> 0.47 | E5: =ROUND(C5/D5/业态参数包!C10,0) -> 993 | F5: =ROUND((C5+10000)/D5/业态参数包!C10,0) -> 1702 | G5: =ROUND((C5+10000)/D5,0) -> 51064 | H5: 客单价低、翻台快；门槛靠日均客流撑
A6: 火锅 | B6: =2*业态参数包!D9 -> 10000 | C6: =5000+B6 -> 15000 | D6: =业态参数包!D12 -> 0.39 | E6: =ROUND(C6/D6/业态参数包!D10,0) -> 1425 | F6: =ROUND((C6+10000)/D6/业态参数包!D10,0) -> 2374 | G6: =ROUND((C6+10000)/D6,0) -> 64103 | H6: 水电燃气高、月休多，保本线被显著抬高
A7: 新式奶茶 | B7: =2*业态参数包!E9 -> 9000 | C7: =5000+B7 -> 14000 | D7: =业态参数包!E12 -> 0.56 | E7: =ROUND(C7/D7/业态参数包!E10,0) -> 833 | F7: =ROUND((C7+10000)/D7/业态参数包!E10,0) -> 1429 | G7: =ROUND((C7+10000)/D7,0) -> 42857 | H7: 食材占比低，保本线最低；但房租承受力弱
A8: 烧烤 | B8: =2*业态参数包!F9 -> 9600 | C8: =5000+B8 -> 14600 | D8: =业态参数包!F12 -> 0.42 | E8: =ROUND(C8/D8/业态参数包!F10,0) -> 1337 | F8: =ROUND((C8+10000)/D8/业态参数包!F10,0) -> 2253 | G8: =ROUND((C8+10000)/D8,0) -> 58571 | H8: 损耗高、营业天数少，同样利润需更高日流水
A11: 结论：同一「30㎡ / 租金 5000 / 2 人 / 月赚 1 万」条件下，四个业态的日营业额门槛可相差约一倍 —— 参数包必须整套独立，不能只换食材率。

Sheet 复现·原小面表校验
A1: 复现校验：原《小面测算.xlsx》口径逐行复算（贡献率 43%）
A2: 原表口径：月人工 = 人数×4500 ｜ 固定成本 = 房租+人工 ｜ 贡献率 = 1−45%食材−5%水电−5%管理−2%杂支 = 43% ｜ 月营业额 =（固定成本+目标净利）÷43% ｜ 日碗数 = 向上取整(月营业额÷12÷30)
A4: 月租金(元) | B4: 人数(人) | C4: 月人工(元) | D4: 月固定成本(元) | E4: 目标 | F4: 目标净利(元) | G4: 原表月营业额 | H4: 复算月营业额 | I4: 差额 | J4: 原表日碗数 | K4: 复算日碗数
A5: 3000 | B5: 2 | C5: =B5*4500 -> 9000 | D5: =A5+C5 -> 12000 | E5: 保本 | F5: 0 | G5: 27907 | H5: =ROUND((D5+F5)/0.43,0) -> 27907 | I5: =H5-G5 -> 0 | J5: 78 | K5: =ROUNDUP(H5/12/30,0) -> 78
A6: 3000 | B6: 2 | C6: =B6*4500 -> 9000 | D6: =A6+C6 -> 12000 | E6: 盈利1万 | F6: 10000 | G6: 51163 | H6: =ROUND((D6+F6)/0.43,0) -> 51163 | I6: =H6-G6 -> 0 | J6: 143 | K6: =ROUNDUP(H6/12/30,0) -> 143
A7: 3000 | B7: 2 | C7: =B7*4500 -> 9000 | D7: =A7+C7 -> 12000 | E7: 盈利1.5万 | F7: 15000 | G7: 62791 | H7: =ROUND((D7+F7)/0.43,0) -> 62791 | I7: =H7-G7 -> 0 | J7: 175 | K7: =ROUNDUP(H7/12/30,0) -> 175
A8: 3000 | B8: 3 | C8: =B8*4500 -> 13500 | D8: =A8+C8 -> 16500 | E8: 保本 | F8: 0 | G8: 38372 | H8: =ROUND((D8+F8)/0.43,0) -> 38372 | I8: =H8-G8 -> 0 | J8: 107 | K8: =ROUNDUP(H8/12/30,0) -> 107
A9: 3000 | B9: 3 | C9: =B9*4500 -> 13500 | D9: =A9+C9 -> 16500 | E9: 盈利1万 | F9: 10000 | G9: 61628 | H9: =ROUND((D9+F9)/0.43,0) -> 61628 | I9: =H9-G9 -> 0 | J9: 172 | K9: =ROUNDUP(H9/12/30,0) -> 172
A10: 3000 | B10: 3 | C10: =B10*4500 -> 13500 | D10: =A10+C10 -> 16500 | E10: 盈利1.5万 | F10: 15000 | G10: 73256 | H10: =ROUND((D10+F10)/0.43,0) -> 73256 | I10: =H10-G10 -> 0 | J10: 204 | K10: =ROUNDUP(H10/12/30,0) -> 204
A11: 4000 | B11: 2 | C11: =B11*4500 -> 9000 | D11: =A11+C11 -> 13000 | E11: 保本 | F11: 0 | G11: 30233 | H11: =ROUND((D11+F11)/0.43,0) -> 30233 | I11: =H11-G11 -> 0 | J11: 84 | K11: =ROUNDUP(H11/12/30,0) -> 84
A12: 4000 | B12: 2 | C12: =B12*4500 -> 9000 | D12: =A12+C12 -> 13000 | E12: 盈利1万 | F12: 10000 | G12: 53488 | H12: =ROUND((D12+F12)/0.43,0) -> 53488 | I12: =H12-G12 -> 0 | J12: 149 | K12: =ROUNDUP(H12/12/30,0) -> 149
A13: 4000 | B13: 2 | C13: =B13*4500 -> 9000 | D13: =A13+C13 -> 13000 | E13: 盈利1.5万 | F13: 15000 | G13: 65116 | H13: =ROUND((D13+F13)/0.43,0) -> 65116 | I13: =H13-G13 -> 0 | J13: 181 | K13: =ROUNDUP(H13/12/30,0) -> 181
A14: 4000 | B14: 3 | C14: =B14*4500 -> 13500 | D14: =A14+C14 -> 17500 | E14: 保本 | F14: 0 | G14: 40698 | H14: =ROUND((D14+F14)/0.43,0) -> 40698 | I14: =H14-G14 -> 0 | J14: 114 | K14: =ROUNDUP(H14/12/30,0) -> 114
A15: 4000 | B15: 3 | C15: =B15*4500 -> 13500 | D15: =A15+C15 -> 17500 | E15: 盈利1万 | F15: 10000 | G15: 63953 | H15: =ROUND((D15+F15)/0.43,0) -> 63953 | I15: =H15-G15 -> 0 | J15: 178 | K15: =ROUNDUP(H15/12/30,0) -> 178
A16: 4000 | B16: 3 | C16: =B16*4500 -> 13500 | D16: =A16+C16 -> 17500 | E16: 盈利1.5万 | F16: 15000 | G16: 75581 | H16: =ROUND((D16+F16)/0.43,0) -> 75581 | I16: =H16-G16 -> 0 | J16: 210 | K16: =ROUNDUP(H16/12/30,0) -> 210
... A52: 10000 | B52: 3 | C52: =B52*4500 -> 13500 | D52: =A52+C52 -> 23500 | E52: 盈利1.5万 | F52: 15000 | G52: 89535 | H52: =ROUND((D52+F52)/0.43,0) -> 89535 | I52: =H52-G52 -> 0 | J52: 249 | K52: =ROUNDUP(H52/12/30,0) -> 249
A54: 对上结论（逐格机器复核）： ① 「差额」列应全为 0 —— 说明复算口径与原表逐行一致，模型可被完整复现。 ② 原表 A 列面积 20/30/40㎡ 三档，除面积列外其余 14 列 48 行数据逐格完全相同 ⇒ 面积对该表结果零影响。本方案把面积改为「合理性校验 + 坪效输出」，不再参与保本公式（中小餐饮面积确实不直接改变保本营业额）。 ③ 原表全表 0 条公式、参数写死在数值里 ⇒ 换业态必须整表重做。本方案改为参数包 + 全公式联动。
